[
  {
    "word": "photosynthesis",
    "meaning_ko": "광합성"
  },
  {
    "word": "gravity",
    "meaning_ko": "중력"
  },
  {
    "word": "atom",
    "meaning_ko": "원자"
  },
  {
    "word": "molecule",
    "meaning_ko": "분자"
  },
  {
    "word": "eclipse",
    "meaning_ko": "식(일식/월식)"
  },
  {
    "word": "voltage",
    "meaning_ko": "전압"
  },
  {
    "word": "friction",
    "meaning_ko": "마찰"
  },
  {
    "word": "inertia",
    "meaning_ko": "관성"
  },
  {
    "word": "orbit",
    "meaning_ko": "궤도"
  },
  {
    "word": "evaporation",
    "meaning_ko": "증발"
  },
  {
    "word": "condensation",
    "meaning_ko": "응결"
  },
  {
    "word": "precipitation",
    "meaning_ko": "강수"
  },
  {
    "word": "density",
    "meaning_ko": "밀도"
  },
  {
    "word": "force",
    "meaning_ko": "힘"
  },
  {
    "word": "energy",
    "meaning_ko": "에너지"
  }
]